ujson_manager/__init__.py
ujson_manager/ujson_manager.py
ujson_manager-1.0.4.dist-info/LICENSE
ujson_manager-1.0.4.dist-info/METADATA
ujson_manager-1.0.4.dist-info/WHEEL
ujson_manager-1.0.4.dist-info/top_level.txt
ujson_manager-1.0.4.dist-info/RECORD
