Metadata-Version: 2.1
Name: ujson_manager
Version: 1.0.4
Author: unixtux
License: GNU GENERAL PUBLIC LICENSE
Project-URL: Repository, https://github.com/unixtux/ujson_manager
Requires-Python: >=3.8
License-File: LICENSE
Requires-Dist: aiotgm
